ContecControllers/ActivationType.py
ContecControllers/CommunicationManager.py
ContecControllers/Conductor.py
ContecControllers/ContecActivation.py
ContecControllers/ContecBlindActivation.py
ContecControllers/ContecConectivityConfiguration.py
ContecControllers/ContecOnOffActivation.py
ContecControllers/ContecPusherActivation.py
ContecControllers/ControllerManager.py
ContecControllers/ControllerUnit.py
ContecControllers/ControllersStatusReader.py
ContecControllers/IControllerUnit.py
ContecControllers/ITracer.py
ContecControllers/RegistersMapping.py
ContecControllers/__init__.py
conteccontrollers-1.0.11.dist-info/licenses/LICENSE
conteccontrollers-1.0.11.dist-info/METADATA
conteccontrollers-1.0.11.dist-info/WHEEL
conteccontrollers-1.0.11.dist-info/top_level.txt
conteccontrollers-1.0.11.dist-info/RECORD
