Metadata-Version: 2.4
Name: ContecControllers
Version: 1.0.11
Summary: Package that use to integrate with Contec controllers
Home-page: https://github.com/havivi86/ContecControllers
Author: Ofir Haviv
Author-email: ofir.haviv@outlook.com
Project-URL: Bug Tracker, https://github.com/havivi86/ContecControllers/issues
Classifier: Programming Language :: Python :: 3
Classifier: License :: OSI Approved :: MIT License
Classifier: Operating System :: OS Independent
Requires-Python: >=3.9
License-File: LICENSE
Requires-Dist: pymodbus>=3.11.1
Dynamic: license-file
